mcp4cm/__init__.py
mcp4cm/base.py
mcp4cm/dataloading.py
mcp4cm/utils.py
mcp4cm/archimate/__init__.py
mcp4cm/archimate/data_extraction.py
mcp4cm/archimate/dataloading.py
mcp4cm/archimate/filtering_patterns.py
mcp4cm/generic/duplicate_detection.py
mcp4cm/generic/filtering_patterns.py
mcp4cm/generic/language_detection.py
mcp4cm/generic/utils.py
mcp4cm/uml/__init__.py
mcp4cm/uml/data_extraction.py
mcp4cm/uml/dataloading.py
mcp4cm/uml/filtering_patterns.py
mcp4cm/uml/utils.py
mcp4cm-1.0.4.dist-info/licenses/LICENSE
mcp4cm-1.0.4.dist-info/METADATA
mcp4cm-1.0.4.dist-info/WHEEL
mcp4cm-1.0.4.dist-info/top_level.txt
mcp4cm-1.0.4.dist-info/RECORD
