Metadata-Version: 2.4
Name: mcp4cm
Version: 1.0.4
Summary: A conceptual models dataset cleaning and preprocessing library
Author-email: Andjela Djelic <andjela.djelic@tuwien.ac.at>, Syed Juned Ali <syed.juned.ali@tuwien.ac.at>
License: MIT License
Project-URL: Homepage, https://github.com/borkdominik/model-cleansing
Project-URL: Issues, https://github.com/borkdominik/model-cleansing/issues
Requires-Python: >=3.8
License-File: LICENSE
Requires-Dist: annotated-types==0.7.0
Requires-Dist: contourpy==1.3.1
Requires-Dist: cycler==0.12.1
Requires-Dist: fonttools==4.56.0
Requires-Dist: joblib==1.4.2
Requires-Dist: kiwisolver==1.4.8
Requires-Dist: langdetect==1.0.9
Requires-Dist: matplotlib==3.10.1
Requires-Dist: numpy==2.2.4
Requires-Dist: packaging==24.2
Requires-Dist: pandas==2.2.3
Requires-Dist: pillow==11.1.0
Requires-Dist: pydantic==2.11.1
Requires-Dist: pydantic-core==2.33.0
Requires-Dist: pyparsing==3.2.3
Requires-Dist: python-dateutil==2.9.0.post0
Requires-Dist: pytz==2025.2
Requires-Dist: scikit-learn==1.6.1
Requires-Dist: scipy==1.15.2
Requires-Dist: seaborn==0.13.2
Requires-Dist: six==1.17.0
Requires-Dist: threadpoolctl==3.6.0
Requires-Dist: typing-extensions==4.13.0
Requires-Dist: typing-inspection==0.4.0
Requires-Dist: tzdata==2025.2
Provides-Extra: dev
Requires-Dist: pytest; extra == "dev"
Requires-Dist: black; extra == "dev"
Dynamic: license-file
